rapidpe_rift_rota_tools/__init__.py
rapidpe_rift_rota_tools/auto_generate_status_page.py
rapidpe_rift_rota_tools/condor.py
rapidpe_rift_rota_tools/create_status_page.py
rapidpe_rift_rota_tools/results.py
rapidpe_rift_rota_tools/status_summary.py
rapidpe_rift_rota_tools/test_statuspage.py
rapidpe_rift_rota_tools/static/__init__.py
rapidpe_rift_rota_tools/static/gracedb_dir.json
rapidpe_rift_rota_tools/template_files/__init__.py
rapidpe_rift_rota_tools/template_files/status.jinja2
rapidpe_rift_rota_tools/template_files/status_style.css
rapidpe_rift_rota_tools/template_files/status_style.js
rapidpe_rift_rota_tools-0.0.3.dist-info/COPYING
rapidpe_rift_rota_tools-0.0.3.dist-info/METADATA
rapidpe_rift_rota_tools-0.0.3.dist-info/WHEEL
rapidpe_rift_rota_tools-0.0.3.dist-info/entry_points.txt
rapidpe_rift_rota_tools-0.0.3.dist-info/top_level.txt
rapidpe_rift_rota_tools-0.0.3.dist-info/RECORD
